pastehunter
