Metadata-Version: 2.1
Name: pastehunter
Version: 1.4.1
Summary: Pastehunter
Home-page: https://pastehunter.com
Author: @kevthehermit @Plazmaz
Author-email: info@pastehunter.com
License: GNU V3
Platform: UNKNOWN
